LICENSE.txt
README.md
setup.py
src/ytbdl/__init__.py
src/ytbdl/application.py
src/ytbdl/beets.py
src/ytbdl/default_config.yaml
src/ytbdl/exceptions.py
src/ytbdl/yt_dlp.py
src/ytbdl.egg-info/PKG-INFO
src/ytbdl.egg-info/SOURCES.txt
src/ytbdl.egg-info/dependency_links.txt
src/ytbdl.egg-info/entry_points.txt
src/ytbdl.egg-info/requires.txt
src/ytbdl.egg-info/top_level.txt
src/ytbdl/apps/__init__.py
src/ytbdl/apps/base.py
src/ytbdl/apps/config.py
src/ytbdl/apps/get.py
src/ytbdl/beetsplug/__init__.py
src/ytbdl/beetsplug/fromdirname.py
src/ytbdl/beetsplug/fromyoutubetitle.py
src/ytbdl/beetsplug/tagsfrompath.py