Metadata-Version: 2.1
Name: ytbdl
Version: 0.0.5
Summary: Download music with yt-dlp and autotag it with beets
Home-page: https://github.com/danloveg/ytbdl
Author: Daniel Lovegrove
Author-email: d.lovegrove11@gmail.com
License: MIT
Platform: UNKNOWN
Requires-Python: >=3.6.0
